README
setup.py
zapian/__init__.py
zapian/api.py
zapian/cjksplitter.py
zapian/query.py
zapian/schema.py
zapian/tests.py
zapian/utils.py
zapian.egg-info/PKG-INFO
zapian.egg-info/SOURCES.txt
zapian.egg-info/dependency_links.txt
zapian.egg-info/namespace_packages.txt
zapian.egg-info/not-zip-safe
zapian.egg-info/requires.txt
zapian.egg-info/top_level.txt