Metadata-Version: 1.1
Name: zapian
Version: 0.3.9
Summary: indexer addons: sort, cjksplitter, and so on
Home-page: http://github.com/everydo/zapian
Author: Pan Junyong
Author-email: dev@zopen.cn
License: Private
Keywords: zope3 z3c rpc  server client
Platform: UNKNOWN
Classifier: Environment :: Web Environment
Classifier: Intended Audience :: Developers
Classifier: Programming Language :: Python
Classifier: Operating System :: OS Independent
Classifier: Topic :: Internet :: WWW/HTTP
Classifier: Framework :: Zope3
